{
  "dependencies": {
    "ChangeLinr": "0.6.0",
    "StringFilr": "0.6.0",
    "MapScreenr": "0.6.0",
    "ItemsHoldr": "0.6.0",
    "BattleMovr": "0.6.0",
    "DeviceLayr": "0.6.0",
    "EightBittr": "0.6.0",
    "AudioPlayr": "0.6.0",
    "FPSAnalyzr": "0.6.0",
    "GamesRunnr": "0.6.0",
    "GroupHoldr": "0.6.0",
    "InputWritr": "0.6.0",
    "MapsCreatr": "0.6.0",
    "MathDecidr": "0.6.0",
    "ModAttachr": "0.6.0",
    "NumberMakr": "0.6.0",
    "ObjectMakr": "0.6.0",
    "QuadsKeepr": "0.6.0",
    "AreaSpawnr": "0.6.0",
    "PixelRendr": "0.6.0",
    "PixelDrawr": "0.6.0",
    "ScenePlayr": "0.6.0",
    "StateHoldr": "0.6.0",
    "ThingHittr": "0.6.0",
    "TimeHandlr": "0.6.0",
    "TouchPassr": "0.6.0",
    "WorldSeedr": "0.6.0",
    "GameStartr": "0.6.0",
    "MenuGraphr": "0.6.0"
  },
  "package": {
    "description": "A user interface wrapper for configurable HTML displays over GameStartr games.",
    "name": "UserWrappr",
    "version": "0.6.0"
  }
}
